pytinyxml2.py
_pytinyxml2.pyd
pytinyxml2-2.1.0.dist-info/DESCRIPTION.rst
pytinyxml2-2.1.0.dist-info/METADATA
pytinyxml2-2.1.0.dist-info/metadata.json
pytinyxml2-2.1.0.dist-info/RECORD
pytinyxml2-2.1.0.dist-info/top_level.txt
pytinyxml2-2.1.0.dist-info/WHEEL
