Metadata-Version: 2.0
Name: pytinyxml2
Version: 2.1.0
Summary: Python wrapper for tinyxml2
Home-page: https://github.com/wiadufachen/pytinyxml2
Author: Wiadufa Chen
Author-email: wiadufachen@gmail.com
License: UNKNOWN
Platform: UNKNOWN
Classifier: Programming Language :: Python
Classifier: Programming Language :: Python :: 3
Classifier: License :: OSI Approved :: Apache Software License
Classifier: Development Status :: 4 - Beta
Classifier: Operating System :: OS Independent
